flask_celery/__init__.py
flask_celery/exceptions.py
flask_celery/lock_manager.py
flask_celery/py.typed
flask_celery/types.py
flask_celery/backends/__init__.py
flask_celery/backends/base.py
flask_celery/backends/filesystem.py
flask_celery/backends/redis.py
flask_celery/backends/database/__init__.py
flask_celery/backends/database/models.py
flask_celery/backends/database/sessions.py
flask_celery_tools-1.5.3.dist-info/licenses/LICENSE
flask_celery_tools-1.5.3.dist-info/METADATA
flask_celery_tools-1.5.3.dist-info/WHEEL
flask_celery_tools-1.5.3.dist-info/top_level.txt
flask_celery_tools-1.5.3.dist-info/RECORD
