Metadata-Version: 2.4
Name: Flask-Celery-Tools
Version: 1.5.3
Summary: Celery support for Flask without breaking PyCharm inspections.
Author-email: Adam Schubert <adam.schubert@sg1-game.net>
License-Expression: MIT
Project-URL: Homepage, https://github.com/Salamek/Flask-Celery-Tools
Classifier: Development Status :: 5 - Production/Stable
Classifier: Environment :: Web Environment
Classifier: Environment :: Console
Classifier: Intended Audience :: Developers
Classifier: Operating System :: OS Independent
Classifier: Framework :: Flask
Classifier: Programming Language :: Python
Classifier: Programming Language :: Python :: Implementation :: CPython
Classifier: Programming Language :: Python :: Implementation :: PyPy
Classifier: Programming Language :: Python :: 3.11
Classifier: Programming Language :: Python :: 3.12
Classifier: Programming Language :: Python :: 3.13
Classifier: Topic :: Software Development
Requires-Python: >=3.11
License-File: LICENSE
Requires-Dist: flask>=1.0.2
Requires-Dist: celery<=5.3.6
Requires-Dist: redis>=3.5.3
Requires-Dist: sqlalchemy>=1.2.7
Provides-Extra: dev
Requires-Dist: ruff; extra == "dev"
Requires-Dist: mypy; extra == "dev"
Requires-Dist: types-setuptools; extra == "dev"
Requires-Dist: flask_sqlalchemy; extra == "dev"
Requires-Dist: flask_redis; extra == "dev"
Provides-Extra: test
Requires-Dist: pytest; extra == "test"
Dynamic: license-file
